zyjj_client_sdk/__init__.py
zyjj_client_sdk/base/__init__.py
zyjj_client_sdk/base/api.py
zyjj_client_sdk/base/base.py
zyjj_client_sdk/base/const.py
zyjj_client_sdk/base/decorator.py
zyjj_client_sdk/base/decorator_test.py
zyjj_client_sdk/base/entity.py
zyjj_client_sdk/base/exception.py
zyjj_client_sdk/base/mqtt.py
zyjj_client_sdk/base/tool.py
zyjj_client_sdk/base/tool_test.py
zyjj_client_sdk/flow/__init__.py
zyjj_client_sdk/flow/base.py
zyjj_client_sdk/flow/base_hint.pyi
zyjj_client_sdk/flow/flow.py
zyjj_client_sdk/flow/node/__init__.py
zyjj_client_sdk/flow/node/base.py
zyjj_client_sdk/flow/node/common.py
zyjj_client_sdk/flow/node/tool.py
zyjj_client_sdk/lib/__init__.py
zyjj_client_sdk/lib/cache.py
zyjj_client_sdk/lib/cache_test.py
zyjj_client_sdk/lib/ffmpeg.py
zyjj_client_sdk/lib/ffmpeg_test.py
zyjj_client_sdk/lib/notify.py
zyjj_client_sdk/lib/oss.py
zyjj_client_sdk/lib/oss_test.py
zyjj_client_sdk/server.py
zyjj_client_sdk-0.2.16.dist-info/METADATA
zyjj_client_sdk-0.2.16.dist-info/WHEEL
zyjj_client_sdk-0.2.16.dist-info/RECORD
