Metadata-Version: 2.3
Name: zyjj-client-sdk
Version: 0.2.16
Summary: 智游剪辑客户端sdk包
Author: xiaoyou
Author-email: xiaoyou2333@foxmail.com
Requires-Python: >=3.9,<4.0
Classifier: Programming Language :: Python :: 3
Classifier: Programming Language :: Python :: 3.9
Classifier: Programming Language :: Python :: 3.10
Classifier: Programming Language :: Python :: 3.11
Classifier: Programming Language :: Python :: 3.12
Classifier: Programming Language :: Python :: 3.13
Requires-Dist: chardet (>=5.2.0,<5.3.0)
Requires-Dist: cos-python-sdk-v5 (>=1.9.26,<1.10.0)
Requires-Dist: graphviz (>=0.20.3,<0.21.0)
Requires-Dist: httpx (>=0.28.1,<0.29.0)
Requires-Dist: json5 (>=0.10.0,<0.11.0)
Requires-Dist: oss2 (>=2.19.0,<2.20.0)
Requires-Dist: paho-mqtt (>=2.1.0,<3.0.0)
Requires-Dist: regex (>=2024.9.11,<2024.10.0)
Requires-Dist: tenacity (>=9.0.0,<9.1.0)
Requires-Dist: tencentcloud-sdk-python (>=3.0.1090,<3.1.0)
